timeseria/__init__.py
timeseria/datastructures.py
timeseria/exceptions.py
timeseria/interpolators.py
timeseria/logger.py
timeseria/operations.py
timeseria/plots.py
timeseria/storages.py
timeseria/transformations.py
timeseria/units.py
timeseria/utils.py
timeseria/models/__init__.py
timeseria/models/anomaly_detectors.py
timeseria/models/base.py
timeseria/models/calibrators.py
timeseria/models/forecasters.py
timeseria/models/forecasters_interval_score.py
timeseria/models/reconstructors.py
timeseria/static/css/dygraph-2.1.0.css
timeseria/static/js/dygraph-2.1.0.min.js
timeseria/tests/__init__.py
timeseria/tests/test_datastructures.py
timeseria/tests/test_models_anomaly_detectors.py
timeseria/tests/test_models_base.py
timeseria/tests/test_models_forecasters.py
timeseria/tests/test_models_reconstructors.py
timeseria/tests/test_operations.py
timeseria/tests/test_plots.py
timeseria/tests/test_storages.py
timeseria/tests/test_transformations.py
timeseria/tests/test_units.py
timeseria/tests/test_utils.py
timeseria/tests/test_data/csv/format1.csv
timeseria/tests/test_data/csv/format2.csv
timeseria/tests/test_data/csv/format3.csv
timeseria/tests/test_data/csv/format4.csv
timeseria/tests/test_data/csv/format5.csv
timeseria/tests/test_data/csv/humitemp.csv
timeseria/tests/test_data/csv/humitemp_long.csv
timeseria/tests/test_data/csv/humitemp_short.csv
timeseria/tests/test_data/csv/multi_values_no_labels.csv
timeseria/tests/test_data/csv/multi_values_with_labels.csv
timeseria/tests/test_data/csv/multi_values_with_labels_dirty.csv
timeseria/tests/test_data/csv/multi_values_with_labels_unordered.csv
timeseria/tests/test_data/csv/no_data.csv
timeseria/tests/test_data/csv/only_date_no_meaningful_timestamp_label.csv
timeseria/tests/test_data/csv/shampoo_sales.csv
timeseria/tests/test_data/csv/single_value_no_labels.csv
timeseria/tests/test_data/csv/single_value_no_labels_dirty.csv
timeseria/tests/test_data/csv/temp_long_10m.csv
timeseria/tests/test_data/csv/temp_long_1h.csv
timeseria-2.3.0.dist-info/LICENSE
timeseria-2.3.0.dist-info/METADATA
timeseria-2.3.0.dist-info/WHEEL
timeseria-2.3.0.dist-info/top_level.txt
timeseria-2.3.0.dist-info/RECORD
