Metadata-Version: 2.1
Name: timeseria
Version: 2.3.0
Summary: An object-oriented time series processing library
Home-page: https://github.com/sarusso/timeseria
Author: Stefano Alberto Russo
Author-email: stefano.russo@gmail.com
License: Apache License 2.0
Platform: UNKNOWN
Requires-Dist: chardet (<4.0.0,>=3.0.4)
Requires-Dist: convertdate (<3.0.0,>=2.1.2)
Requires-Dist: cython (<1.0.0,>=0.29.17)
Requires-Dist: fitter (==1.7.0)
Requires-Dist: lunarcalendar (<1.0.0,>=0.0.9)
Requires-Dist: matplotlib (<4.0.0,>=2.1.2)
Requires-Dist: numpy (<2.0.0,>=1.19.5)
Requires-Dist: pandas (<2.0.0,>=0.23.4)
Requires-Dist: propertime (<2.0.0,>=1.0.1)
Requires-Dist: pyppeteer (<1.0.0,>=0.2.6)
Requires-Dist: requests (<3.0.0,>=2.20.0)
Requires-Dist: scikit-learn (<2.0.0,>=0.2.2)
Requires-Dist: scipy (<2.0.0,>=1.5.4)
Provides-Extra: arima
Requires-Dist: pmdarima (<3.0.0,>=1.8) ; extra == 'arima'
Requires-Dist: statsmodels (<1.0.0,>=0.14.0) ; extra == 'arima'
Provides-Extra: prophet
Requires-Dist: prophet (<2.0.0,>=1.1.1) ; extra == 'prophet'
Provides-Extra: tensorflow
Requires-Dist: tensorflow (<3.0.0,>=2.0.0) ; extra == 'tensorflow'
Provides-Extra: tensorflow-aarch64
Requires-Dist: tensorflow-aarch64 (<3.0.0,>=2.0.0) ; extra == 'tensorflow-aarch64'
Provides-Extra: tensorflow-gpu
Requires-Dist: tensorflow-gpu (<3.0.0,>=2.0.0) ; extra == 'tensorflow-gpu'
Provides-Extra: tensorflow-macos
Requires-Dist: tensorflow-macos (<3.0.0,>=2.0.0) ; extra == 'tensorflow-macos'
